psrn/__init__.py
psrn/cli.py
psrn/data/custom_data.csv
psrn/data/custom_data2.csv
psrn/dr_mask/3_10_[Add_Mul_Identity_Neg_Inv_Sin_Cos_Exp_Log]_mask.npy
psrn/dr_mask/3_2_[Add_Mul_Identity]_mask.npy
psrn/dr_mask/3_2_[Add_Mul_Identity_Tanh_Abs]_mask.npy
psrn/dr_mask/3_2_[Add_Mul_Sub_Div_Identity_Sin_Cos_Exp_Log]_mask.npy
psrn/dr_mask/3_2_[Add_Mul_Sub_Div_Identity_Sin_Exp]_mask.npy
psrn/dr_mask/3_3_[Add_Mul_Sub_Div_Identity_Sin_Cos_Exp_Log]_mask.npy
psrn/dr_mask/3_3_[Add_Mul_Sub_Div_Identity_Sin_Exp]_mask.npy
psrn/dr_mask/3_3_[Add_Mul_Sub_Div_Identity_Sin_Exp_Sign]_mask.npy
psrn/dr_mask/3_3_[Add_Mul_Sub_Div_Identity_Sin_Sign]_mask.npy
psrn/dr_mask/3_3_[Add_Mul_Sub_Div_Identity_Tanh_Abs]_mask.npy
psrn/dr_mask/3_3_[Add_Mul_Sub_Div_Identity_Tanh_Exp]_mask.npy
psrn/dr_mask/3_3_[Add_Mul_Sub_Div_Identity_Tanh_Sin]_mask.npy
psrn/dr_mask/3_3_[Mul_Identity_Tanh_Abs]_mask.npy
psrn/dr_mask/3_4_[Add_Mul_SemiSub_SemiDiv_Identity_Neg_Inv_Sin_Cos_Exp_Log_Sqrt_Pow3]_mask.npy
psrn/dr_mask/3_4_[Add_Mul_Sub_Div_Identity_Sin_Cos_Exp_Log]_mask.npy
psrn/dr_mask/3_5_[Add_Mul_Div_Sub_Identity_Sign]_mask.npy
psrn/dr_mask/3_5_[Add_Mul_Identity]_mask.npy
psrn/dr_mask/3_5_[Add_Mul_Identity_Neg_Inv_Sin_Cos_Exp_Log]_mask.npy
psrn/dr_mask/3_5_[Add_Mul_Identity_Tanh]_mask.npy
psrn/dr_mask/3_5_[Add_Mul_Identity_Tanh_Abs]_mask.npy
psrn/dr_mask/3_5_[Add_Mul_Pow_Div_Identity]_mask.npy
psrn/dr_mask/3_5_[Add_Mul_Pow_Div_Identity_Pow2_Pow3]_mask.npy
psrn/dr_mask/3_5_[Add_Mul_Pow_Div_Identity_Pow2_Pow3_Inv_Neg_Sqrt]_mask.npy
psrn/dr_mask/3_5_[Add_Mul_Pow_Identity]_mask.npy
psrn/dr_mask/3_5_[Add_Mul_Pow_Identity_Neg_Inv]_mask.npy
psrn/dr_mask/3_5_[Add_Mul_Pow_Identity_Neg_Inv_Exp_Log]_mask.npy
psrn/dr_mask/3_5_[Add_Mul_Pow_Identity_Pow2_Pow3_Inv_Neg]_mask.npy
psrn/dr_mask/3_5_[Add_Mul_Pow_Identity_Pow2_Pow3_Inv_Neg_Cos_Cosh_Exp_Log_Sin_Tanh]_mask.npy
psrn/dr_mask/3_5_[Add_Mul_Pow_Identity_Pow2_Pow3_Inv_Neg_Cos_Cosh_Exp_Log_Sin_Tanh_Sqrt]_mask.npy
psrn-0.1.2.dist-info/licenses/LICENSE
psrn-0.1.2.dist-info/METADATA
psrn-0.1.2.dist-info/WHEEL
psrn-0.1.2.dist-info/entry_points.txt
psrn-0.1.2.dist-info/top_level.txt
psrn-0.1.2.dist-info/RECORD
