Metadata-Version: 2.4
Name: psrn
Version: 0.1.2
Summary: Parallel Symbolic Regression Network (PSRN) / Parallel Symbolic Enumeration (PSE)
Author-email: Kai Ruan <kairuan@ruc.edu.cn>
License: MIT License
Project-URL: Homepage, https://github.com/x66ccff/PSRN
Project-URL: Paper, https://www.nature.com/articles/s43588-025-00904-8
Keywords: symbolic regression,AI4Science,pytorch,scientific discovery
Classifier: Programming Language :: Python :: 3
Classifier: Programming Language :: Python :: 3.9
Classifier: Programming Language :: Python :: 3.10
Classifier: Programming Language :: Python :: 3.11
Classifier: Programming Language :: Python :: 3.12
Classifier: Operating System :: OS Independent
Classifier: Topic :: Scientific/Engineering :: Artificial Intelligence
Requires-Python: >=3.9
License-File: LICENSE
Requires-Dist: torch>=2.0.0
Requires-Dist: deap==1.3.3
Requires-Dist: numpy
Requires-Dist: pandas
Requires-Dist: scikit-learn
Requires-Dist: PyYAML
Requires-Dist: sympy
Requires-Dist: numba
Requires-Dist: tqdm
Requires-Dist: scipy
Requires-Dist: click
Requires-Dist: symengine==0.11.0
Dynamic: license-file
